{"typhoon":[
{"ycoeff":"4.87948","number":"1609","name":"台風9号:ミンドゥル","xshift":"0","img":"https://mws.cdn.weathernews.jp/ip/ty17/1609x1a.png?2498712","details":[{"pressure":"992hPa","longitude":"東経 145度 0分","location":"網走市の北北東 約130km","date":"現在地の情報","maxwind":"25m/s","strength":"--","size":"--","windgust":"35m/s","direction":"北北東  75km/h","latitude":"北緯  45度 5分"},{"pressure":"992hPa","longitude":"東経 146度 0分","location":"--","date":"23日15時の予報","maxwind":"25m/s","strength":"--","size":"--","windgust":"35m/s","direction":"北  65km/h","latitude":"北緯  48度 5分"},{"pressure":"992hPa","longitude":"東経 147度35分","location":"オホーツク海","date":"23日21時の予報","maxwind":"23m/s","strength":"--","size":"--","windgust":"35m/s","direction":"北北東  65km/h","latitude":"北緯  52度10分"},{"pressure":"990hPa","longitude":"東経 148度30分","location":"--","date":"24日03時の予報","maxwind":"23m/s","strength":"--","size":"--","windgust":"35m/s","direction":"北  55km/h","latitude":"北緯  55度40分"},{"pressure":"984hPa","longitude":"東経 149度 0分","location":"オホーツク海","date":"24日09時の予報","maxwind":"20m/s","strength":"--","size":"--","windgust":"30m/s","direction":"北  55km/h","latitude":"北緯  58度 0分"}],"comment_title":"台風9号、温帯低気圧へ","storm_img":"https://mws.cdn.weathernews.jp/ip/ty17/1609x1b.png?2498712","img_large":"https://mws.cdn.weathernews.jp/ip/ty17/1609x3a.png?2498712","xcoeff":"4.94672","storm_img_large":"https://mws.cdn.weathernews.jp/ip/ty17/1609x3b.png?2498712","yshift":"0","comment_body":"台風9号は、23日(火)12時にオホーツク海上で温帯低気圧に変わりました。"},

{"ycoeff":"4.87948","number":"1616","name":"台風16号:マラカス","xshift":"0","img":"https://mws.cdn.weathernews.jp/ip/ty17/1616x1a.png?2498712","details":[{"pressure":"1000hPa","longitude":"東経 137度30分","location":"豊橋市の付近","date":"現在地の情報","maxwind":"20m/s","strength":"--","size":"--","windgust":"30m/s","direction":"東  30km/h","latitude":"北緯  34度50分"},{"pressure":"996hPa","longitude":"東経 139度 5分","location":"--","date":"21日00時の予報","maxwind":"20m/s","strength":"--","size":"--","windgust":"30m/s","direction":"東  30km/h","latitude":"北緯  35度20分"},{"pressure":"1000hPa","longitude":"東経 141度30分","location":"銚子市の東 約60km","date":"21日06時の予報","maxwind":"18m/s","strength":"--","size":"--","windgust":"25m/s","direction":"東  40km/h","latitude":"北緯  35度35分"},{"pressure":"1004hPa","longitude":"東経 143度55分","location":"--","date":"21日12時の予報","maxwind":"18m/s","strength":"--","size":"--","windgust":"25m/s","direction":"東  35km/h","latitude":"北緯  35度50分"},{"pressure":"1008hPa","longitude":"東経 146度 5分","location":"日本の東","date":"21日18時の予報","maxwind":"18m/s","strength":"--","size":"--","windgust":"25m/s","direction":"東  35km/h","latitude":"北緯  36度 0分"}],"comment_title":"---","storm_img":"https://mws.cdn.weathernews.jp/ip/ty17/1616x1b.png?2498712","img_large":"https://mws.cdn.weathernews.jp/ip/ty17/1616x3a.png?2498712","xcoeff":"4.94672","storm_img_large":"https://mws.cdn.weathernews.jp/ip/ty17/1616x3b.png?2498712","yshift":"0","comment_body":"---"},

{"ycoeff":"4.87948","number":"1618","name":"台風18号:チャバ","xshift":"0","img":"https://mws.cdn.weathernews.jp/ip/ty17/1618x1a.png?2498712","details":[{"pressure":"980hPa","longitude":"東経 135度20分","location":"輪島市の西 約140km","date":"現在地の情報","maxwind":"30m/s","strength":"--","size":"--","windgust":"45m/s","direction":"東北東  80km/h","latitude":"北緯  37度35分"},{"pressure":"988hPa","longitude":"東経 138度 5分","location":"--","date":"06日00時の予報","maxwind":"25m/s","strength":"--","size":"--","windgust":"35m/s","direction":"東北東  75km/h","latitude":"北緯  38度25分"},{"pressure":"996hPa","longitude":"東経 144度55分","location":"日本の東","date":"06日06時の予報","maxwind":"25m/s","strength":"--","size":"--","windgust":"35m/s","direction":"東北東  85km/h","latitude":"北緯  40度30分"},{"pressure":"994hPa","longitude":"東経 150度 5分","location":"--","date":"06日12時の予報","maxwind":"23m/s","strength":"--","size":"--","windgust":"35m/s","direction":"東北東  75km/h","latitude":"北緯  42度 5分"},{"pressure":"990hPa","longitude":"東経 155度20分","location":"日本のはるか東","date":"06日18時の予報","maxwind":"23m/s","strength":"--","size":"--","windgust":"35m/s","direction":"東北東  75km/h","latitude":"北緯  43度25分"}],"comment_title":"台風18号、温帯低気圧へ","storm_img":"https://mws.cdn.weathernews.jp/ip/ty17/1618x1b.png?2498712","img_large":"https://mws.cdn.weathernews.jp/ip/ty17/1618x3a.png?2498712","xcoeff":"4.94672","storm_img_large":"https://mws.cdn.weathernews.jp/ip/ty17/1618x3b.png?2498712","yshift":"0","comment_body":"台風18号（チャバ）は、21時に温帯低気圧に変わりました。ただ､引き続き北陸や東北の日本海沿岸では暴風に警戒が必要です。また、近畿から東北の広いエリアで大雨や強風、高波に注意が必要です。チャバ：タイの言葉で「ハイビスカス」"}

],"button_list":[{"btn_width":"","btn_url":"https://weathernews.jp/s/news/typh/?fm=typhoon_ch","btn_top":"10","btn_left":"15","btn_title":"今年の台風傾向を解説","btn_img":"","btn_height":"","btn_type":"1"},{"btn_width":"120","btn_url":"https://weathernews.jp/smart/wnt_sample/index_t.html?menu=typhoon_3models&ver=5.9.0","btn_top":"55","btn_left":"15","btn_title":"3本の予測","btn_img":"https://mwsgvs.weathernews.jp/ip/typhoon/icon/button_typhoon_3models@2x.png","btn_height":"50","btn_type":"2"},{"btn_width":"120","btn_url":"https://weathernews.jp/smart/typh/pinpoint.html","btn_top":"105","btn_left":"15","btn_title":"台風ピンポイント","btn_img":"https://mwsgvs.weathernews.jp/ip/typhoon/icon/button_typhoon_pinpoint@2x.png","btn_height":"50","btn_type":"2"},{"btn_width":"120","btn_url":"https://weathernews.jp/smart/typh/traffic.html?fm=typhoon_ch","btn_top":"155","btn_left":"15","btn_title":"交通への影響","btn_img":"https://mwsgvs.weathernews.jp/ip/typhoon/icon/button_typhoon_traffic@2x.png","btn_height":"50","btn_type":"2"}]}
